triss/__init__.py
triss/__main__.py
triss/byte_streams.py
triss/cli.py
triss/core.py
triss/crypto.py
triss/header.py
triss/image.py
triss/paper.py
triss/util.py
triss/codec/__init__.py
triss/codec/data_file.py
triss/codec/memory.py
triss/codec/qrcode.py
triss-2.4.dist-info/COPYING
triss-2.4.dist-info/METADATA
triss-2.4.dist-info/WHEEL
triss-2.4.dist-info/entry_points.txt
triss-2.4.dist-info/top_level.txt
triss-2.4.dist-info/RECORD
