Metadata-Version: 2.1
Name: triss
Version: 2.4
Summary: Trivial secret sharing with authentication, support for M-of-N splits, and paper backups.
Author-email: Philip Brown <pdbrown.git@gmail.com>
Project-URL: Homepage, https://github.com/pdbrown/triss
Project-URL: Bug Tracker, https://github.com/pdbrown/triss/issues
Classifier: Programming Language :: Python :: 3
Classifier: License :: OSI Approved :: GNU General Public License v3 or later (GPLv3+)
Classifier: Operating System :: OS Independent
Requires-Python: >=3.11
License-File: COPYING
Requires-Dist: pillow==11.0.0
Provides-Extra: test
Requires-Dist: pytest==8.3.4; extra == "test"
Requires-Dist: hypothesis==6.123.2; extra == "test"
